{"name":"angular-tools-html_expression_extractor","qualifiedName":"angular-tools-html_expression_extractor","comment":"","variables":{},"functions":{"setters":{},"getters":{},"constructors":{},"operators":{},"methods":{"main":{"name":"main","qualifiedName":"angular-tools-html_expression_extractor.main","comment":"","commentFrom":"","inheritedFrom":"","static":"false","abstract":"false","constant":"false","return":[{"outer":"dynamic","inner":[]}],"parameters":{"args":{"name":"args","optional":"false","named":"false","default":"false","type":[{"outer":"dynamic","inner":[]}],"value":"null","annotations":[]}},"annotations":[]}}},"classes":{"class":[{"name":"FileSourcePrinter","qualifiedName":"angular-tools-html_expression_extractor.FileSourcePrinter"}],"typedef":{},"error":[]},"packageName":"","packageIntro":""}